<?xml version="1.0" encoding="UTF-8"?>
<panorama apprev="17856" id="node1" appversion="6.1.1">
  <input leveltilesize="510" overlap="1" levelingpitch="0" levelingroll="0" width="1000" leveltileurl="tiles/node1/cf_%c/l_%l/c_%x/tile_%y.jpg" levelbiashidpi="1.000" height="1000" levelbias="0.400">
    <level predecode="0" width="1000" preload="0" height="1000"/>
    <level predecode="1" width="500" preload="1" height="500"/>
    <preview color="0x808080" strip="1"/>
  </input>
  <view pannorth="0" fovmode="0">
    <start projection="4" tilt="0" pan="0" fov="70"/>
    <flyin projection="9" tilt="-90" pan="0" fov="170"/>
    <min fovpixel="2" tilt="-90" pan="0"/>
    <max fovstereographic="270" tilt="90" fovfisheye="360" scaletofit="1" pan="360" fov="120"/>
  </view>
  <userdata tags="" description="" source="" latitude="" customnodeid="" longitude="" nodeid="node1" comment="" title="" datetime="" info="" author="" copyright=""/>
  <hotspots wordwrap="1" width="180" height="20">
    <label background="1" bordercolor="0x000000" borderradius="1" backgroundcolor="0xffffff" textcolor="0x000000" textalpha="1" borderalpha="1" wordwrap="1" width="180" backgroundalpha="1" border="1" enabled="1" height="20"/>
    <polystyle mode="0" bordercolor="0x0000ff" handcursor="1" backgroundcolor="0x0000ff" borderalpha="1" backgroundalpha="0.25098"/>
    <hotspot description="" target="_self" skinid="ht_url" tilt="1.35" title="scene4" id="Point01" pan="-348.77" url="file:///Volumes/ANJALI/AnjaliSubmission/Output/scene3/output/scene4/scene4.html"/>
  </hotspots>
  <media>
    <image rotx="0.000" rotz="0.000" handcursor="0" tilt="0.010" stretch="1.000" id="Element02" pan="-0.090" width="1000" fov="90.000" roty="0.000" height="1000" clickmode="0">
      <source url="media/front.jpg"/>
    </image>
    <image rotx="0.000" rotz="0.000" handcursor="0" tilt="-0.220" stretch="1.000" id="Element01" pan="-89.910" width="1000" fov="90.000" roty="0.000" height="1000" clickmode="0">
      <source url="media/right.jpg"/>
    </image>
    <image rotx="0.000" rotz="0.000" handcursor="0" tilt="-0.360" stretch="1.000" id="Element03" pan="-179.860" width="1000" fov="90.000" roty="0.000" height="1000" clickmode="0">
      <source url="media/back.jpg"/>
    </image>
    <image rotx="0.000" rotz="0.000" handcursor="0" tilt="-0.640" stretch="1.000" id="Element04" pan="-269.890" width="1000" fov="90.000" roty="0.000" height="1000" clickmode="0">
      <source url="media/left.jpg"/>
    </image>
    <image rotx="-1.000" rotz="-44.000" handcursor="0" tilt="89.450" stretch="1.000" id="Element05" pan="-585.610" width="1000" fov="90.000" roty="1.000" height="1000" clickmode="0">
      <source url="media/top.jpg"/>
    </image>
    <image rotx="1.000" rotz="51.000" handcursor="0" tilt="-88.400" stretch="1.000" id="Element06" pan="-40.530" width="1000" fov="90.000" roty="1.000" height="1000" clickmode="0">
      <source url="media/floor.jpg"/>
    </image>
    <image rotx="-31.000" rotz="0.000" handcursor="0" tilt="-19.770" stretch="1.000" id="Element07" pan="-40.420" width="2446" fov="43.971" roty="0.000" height="1114" clickmode="0">
      <source url="media/text1.png"/>
    </image>
    <image rotx="0.000" rotz="-97.000" handcursor="0" tilt="-12.240" stretch="1.000" id="Element08" pan="-347.440" width="1221" fov="9.856" roty="0.000" height="775" clickmode="0">
      <source url="media/arrow.png"/>
    </image>
  </media>
  <transition softedge="0" type="crossdissolve" zoomspeed="2" zoomfov="20" zoomin="0" blendcolor="0x000000" zoomoutpause="1" zoomout="0" enabled="1" blendtime="1"/>
  <animation animsequence="Animation01" useinautorotation="0" syncanimationwithvideo="0"/>
  <control rubberband="0" simulatemass="1" contextprojections="0" invertcontrol="1" hideabout="0" lockedwheel="0" lockedkeyboard="0" lockedkeyboardzoom="0" invertwheel="0" speedwheel="1" contextfullscreen="1" sensitivity="8" lockedmouse="0" dblclickfullscreen="0"/>
</panorama>
